rendersrt/__init__.py
rendersrt-0.0.8.dist-info/METADATA
rendersrt-0.0.8.dist-info/WHEEL
rendersrt-0.0.8.dist-info/entry_points.txt
rendersrt-0.0.8.dist-info/top_level.txt
rendersrt-0.0.8.dist-info/RECORD
