Metadata-Version: 2.1
Name: rendersrt
Version: 0.0.8
Summary: a utility for rendering subtitle file into video file
Home-page: https://github.com/botbahlul/rendersrt
Author: Bot Bahlul
Author-email: bot.bahlul@gmail.com
License: MIT License
Requires-Dist: pysrt (>=1.0.1)
Requires-Dist: progressbar2 (>=3.34.3)
